TODO.txt
setup.py
iw/__init__.py
iw.recipe.fetcher.egg-info/PKG-INFO
iw.recipe.fetcher.egg-info/SOURCES.txt
iw.recipe.fetcher.egg-info/dependency_links.txt
iw.recipe.fetcher.egg-info/entry_points.txt
iw.recipe.fetcher.egg-info/namespace_packages.txt
iw.recipe.fetcher.egg-info/not-zip-safe
iw.recipe.fetcher.egg-info/requires.txt
iw.recipe.fetcher.egg-info/top_level.txt
iw/recipe/__init__.py
iw/recipe/fetcher/README.txt
iw/recipe/fetcher/__init__.py
iw/recipe/fetcher/docs/README.txt
iw/recipe/fetcher/doctests/README.txt
iw/recipe/fetcher/tests/__init__.py
iw/recipe/fetcher/tests/test_fetcherdocs.py
