Metadata-Version: 1.0
Name: iw.recipe.fetcher
Version: 0.2
Summary: ZC buildout recipe to fetch urls
Home-page: UNKNOWN
Author: Ingeniweb
Author-email: support@ingeniweb.com
License: GPL
Platform: UNKNOWN
Classifier: Programming Language :: Python
Classifier: Topic :: Software Development :: Libraries :: Python Modules
